ecis_processing/__init__.py
ecis_processing/__main__.py
ecis_processing/data_processor.py
ecis_processing/diagnosis_data_processor.py
ecis_processing/interval_data_processor.py
ecis_processing/medication_data_processor.py
ecis_processing/note_data_processor.py
ecis_processing/patient_data_processor.py
ecis_processing-0.6.0.dist-info/entry_points.txt
ecis_processing-0.6.0.dist-info/LICENSE
ecis_processing-0.6.0.dist-info/WHEEL
ecis_processing-0.6.0.dist-info/METADATA
ecis_processing-0.6.0.dist-info/RECORD
